pyrobinhood/__init__.py
pyrobinhood/account.py
pyrobinhood/auth_provider.py
pyrobinhood/authentication.py
pyrobinhood/instrument.py
pyrobinhood/options.py
pyrobinhood/order.py
pyrobinhood/pyrobinhood.py
pyrobinhood/quote.py
pyrobinhood/token.py
pyrobinhood-0.2.dist-info/METADATA
pyrobinhood-0.2.dist-info/RECORD
pyrobinhood-0.2.dist-info/WHEEL
pyrobinhood-0.2.dist-info/top_level.txt
test/__init__.py
test/test.py
