Metadata-Version: 2.1
Name: pyrobinhood
Version: 0.2
Summary: Python Robinhood client
Home-page: UNKNOWN
Author: Daniel Wang
Author-email: danielwpz@gmail.com
License: MIT
Platform: UNKNOWN
Requires-Dist: requests
